main.py
pickaxe_mcp_web_search-0.1.1.dist-info/METADATA
pickaxe_mcp_web_search-0.1.1.dist-info/WHEEL
pickaxe_mcp_web_search-0.1.1.dist-info/entry_points.txt
pickaxe_mcp_web_search-0.1.1.dist-info/top_level.txt
pickaxe_mcp_web_search-0.1.1.dist-info/RECORD
