Metadata-Version: 2.4
Name: pickaxe-mcp-web-search
Version: 0.1.1
Summary: A simple web search MCP server.
Requires-Python: >=3.12
Requires-Dist: httpx>=0.28.1
Requires-Dist: mcp[cli]>=1.9.3
Requires-Dist: openai>=1.82.0
Requires-Dist: fastmcp>=2.7.0
